best_schedule/__init__.py
best_schedule/main.py
best_schedule/memory.py
best_schedule/memory2.py
best_schedule/memory3.py
best_schedule/memory4.py
best_schedule/memory5.py
best_schedule/memory6.py
best_schedule-1.0.1.dist-info/METADATA
best_schedule-1.0.1.dist-info/WHEEL
best_schedule-1.0.1.dist-info/top_level.txt
best_schedule-1.0.1.dist-info/RECORD
